UcsbAnIntroductionToNumpyAndScipy/README.md
UcsbAnIntroductionToNumpyAndScipy/__init__.py
UcsbAnIntroductionToNumpyAndScipy/__main__.py
UcsbAnIntroductionToNumpyAndScipy/file.pdf
UcsbAnIntroductionToNumpyAndScipy/index.html
ucsb_an_introduction_to_numpy_and_scipy-2024.3.2.0.dist-info/METADATA
ucsb_an_introduction_to_numpy_and_scipy-2024.3.2.0.dist-info/WHEEL
ucsb_an_introduction_to_numpy_and_scipy-2024.3.2.0.dist-info/entry_points.txt
ucsb_an_introduction_to_numpy_and_scipy-2024.3.2.0.dist-info/top_level.txt
ucsb_an_introduction_to_numpy_and_scipy-2024.3.2.0.dist-info/RECORD
